anime_cli/__init__.py
anime_cli/__main__.py
anime_cli/anime.py
anime_cli/proxy_server.py
anime_cli/search/__init__.py
anime_cli/search/gogoanime.py
anime_cli-0.3.3.dist-info/entry_points.txt
anime_cli-0.3.3.dist-info/LICENSE
anime_cli-0.3.3.dist-info/WHEEL
anime_cli-0.3.3.dist-info/METADATA
anime_cli-0.3.3.dist-info/RECORD
