Metadata-Version: 2.1
Name: anime-cli
Version: 0.3.3
Summary: A python based anime cli, search, download watch animes. (Works on Windows too)
Home-page: https://github.com/chirag-droid/anime-cli
License: MIT
Author: Chirag Singla
Author-email: chirag.singla.pi@gmail.com
Requires-Python: >=3.9,<4.0
Classifier: Development Status :: 4 - Beta
Classifier: Environment :: Console
Classifier: License :: OSI Approved :: MIT License
Classifier: License :: Public Domain
Classifier: Natural Language :: English
Classifier: Programming Language :: Python :: 3
Classifier: Programming Language :: Python :: 3.9
Classifier: Topic :: Games/Entertainment
Requires-Dist: bs4 (>=0.0.1,<0.0.2)
Requires-Dist: html5lib (>=1.1,<2.0)
Requires-Dist: inquirerpy (>=0.3.0,<0.4.0)
Requires-Dist: requests (>=2.26.0,<3.0.0)
Project-URL: Repository, https://github.com/chirag-droid/anime-cli
